ocpy/__init__.py
ocpy/acl_template.xml
ocpy/api/__init__.py
ocpy/api/admin_ui/__init__.py
ocpy/api/admin_ui/attachments_info.txt
ocpy/api/admin_ui/event.py
ocpy/api/admin_ui/index.py
ocpy/api/admin_ui/resources.py
ocpy/api/admin_ui/service.py
ocpy/api/admin_ui/themes.py
ocpy/api/api_client.py
ocpy/api/assets.py
ocpy/api/external/__init__.py
ocpy/api/external/agents.py
ocpy/api/external/base.py
ocpy/api/external/events.py
ocpy/api/external/groups.py
ocpy/api/external/index.py
ocpy/api/external/series.py
ocpy/api/external/users.py
ocpy/api/external/workflows.py
ocpy/api/info.py
ocpy/api/ingest.py
ocpy/api/org.py
ocpy/api/recordings.py
ocpy/api/search.py
ocpy/api/service.py
ocpy/api/sign.py
ocpy/api/upload.py
ocpy/api/workflow.py
ocpy/model/__init__.py
ocpy/model/acl.py
ocpy/model/event_models.py
ocpy/model/mediapackage.py
ocpy/model/organization.py
ocpy/model/publication.py
ocpy/model/scheduling.py
ocpy/model/server.py
ocpy/model/track.py
ocpy/services/__init__.py
ocpy/services/test.py
ocpy/utils.py
ocpy_client-1.6.1.dist-info/METADATA
ocpy_client-1.6.1.dist-info/WHEEL
ocpy_client-1.6.1.dist-info/entry_points.txt
ocpy_client-1.6.1.dist-info/licenses/LICENSE
ocpy_client-1.6.1.dist-info/RECORD
