Metadata-Version: 2.1
Name: ocpy-client
Version: 1.6.1
Summary: Python client library to access the different APIs of OpenCast, partially tested with OC16.
Author-Email: Tobias Kurze <it@t-kurze.de>
License: GPL
Requires-Python: <4,>=3.8
Requires-Dist: requests<3,>=2
Requires-Dist: xmltodict<1,>=0
Requires-Dist: PyYAML<7,>=6
Requires-Dist: loguru<1,>=0
Requires-Dist: pre-commit<3,>=2
Requires-Dist: pendulum<4,>=3
Requires-Dist: python-dotenv<2,>=1
Requires-Dist: typing-extensions>=4.13.2
